ginger/__main__.py
ginger_emulator-0.2.7.dist-info/LICENSE
ginger_emulator-0.2.7.dist-info/METADATA
ginger_emulator-0.2.7.dist-info/WHEEL
ginger_emulator-0.2.7.dist-info/entry_points.txt
ginger_emulator-0.2.7.dist-info/top_level.txt
ginger_emulator-0.2.7.dist-info/RECORD
