Metadata-Version: 2.1
Name: ginger-emulator
Version: 0.2.7
Summary: GAL equation solver
Author-email: Andrew Dunai <a@dun.ai>
Project-URL: Homepage, https://github.com/and3rson/ginger
Classifier: Programming Language :: Python :: 3
Classifier: License :: OSI Approved :: MIT License
Classifier: Operating System :: OS Independent
Requires-Python: >=3.7
License-File: LICENSE
Requires-Dist: lark ~=1.1.5
